Metadata-Version: 2.1
Name: geography-tour-ready
Version: 0.5
Summary: You can explore
Author: Divyanshi
License: UNKNOWN
Platform: UNKNOWN
